{
  "generatedAt": "2026-07-19T13:18:22.867127+00:00",
  "model": "glm-4-flash",
  "sourceStats": [
    {
      "id": "bbc",
      "name": "BBC World",
      "count": 20,
      "ok": true
    },
    {
      "id": "nyt",
      "name": "NYT World",
      "count": 20,
      "ok": true
    },
    {
      "id": "guardian",
      "name": "The Guardian",
      "count": 20,
      "ok": true
    },
    {
      "id": "npr",
      "name": "NPR News",
      "count": 10,
      "ok": true
    },
    {
      "id": "dw",
      "name": "Deutsche Welle",
      "count": 20,
      "ok": true
    },
    {
      "id": "cnbc",
      "name": "CNBC World",
      "count": 20,
      "ok": true
    },
    {
      "id": "hackernews",
      "name": "Hacker News",
      "count": 30,
      "ok": true
    },
    {
      "id": "gn-cn",
      "name": "Google 新闻 · 中文",
      "count": 20,
      "ok": true
    },
    {
      "id": "weibo",
      "name": "微博热搜",
      "count": 20,
      "ok": true
    },
    {
      "id": "zhihu",
      "name": "知乎热榜",
      "count": 20,
      "ok": true
    },
    {
      "id": "baidu",
      "name": "百度热搜",
      "count": 20,
      "ok": true
    },
    {
      "id": "bili",
      "name": "哔哩哔哩热搜",
      "count": 20,
      "ok": true
    },
    {
      "id": "douyin",
      "name": "抖音热点",
      "count": 20,
      "ok": true
    },
    {
      "id": "toutiao",
      "name": "今日头条",
      "count": 20,
      "ok": true
    }
  ],
  "sections": {
    "international": {
      "title": "国际热点 20",
      "digest": "今日国际局势中，地缘政治紧张局势持续发酵。俄罗斯对乌克兰的袭击引发国际关注，美伊交火事件亦不容忽视。同时，全球范围内，从经济、社会到环境问题，各类事件交织。欧盟边境系统引发护照检查延误，德国加强反洗钱措施，全球范围内的自然灾害和公共卫生问题亦不容忽视。在诸多事件中，俄罗斯加强对反战言论的打压，匈牙利总统提前结束任期等事件值得关注。整体而言，国际局势复杂多变，地缘政治风险和经济挑战并存。",
      "totalSelected": 20,
      "items": [
        {
          "title": "俄罗斯对乌克兰城市发动大规模弹道导弹袭击",
          "titleOrig": "Russia launches major ballistic missile attack on Ukrainian cities",
          "url": "https://www.bbc.co.uk/news/articles/c2el7xpnzrpo?at_medium=RSS&at_campaign=rss",
          "source": "BBC World",
          "sourceId": "bbc",
          "tier": "s",
          "cat": "intl",
          "region": "英国",
          "lang": "en",
          "publishedAt": "2026-07-19T11:28:24+00:00",
          "desc": "Four people are killed and at least 36 injured as Ukraine's two largest cities are targeted, as Kyiv continues its own assault on Russian infrastructure.",
          "hotLabel": "",
          "summary": "俄罗斯对乌克兰两大城市发动袭击，造成人员伤亡。",
          "analysis": "俄罗斯对乌克兰的袭击表明乌克兰冲突持续升级，俄罗斯可能试图通过军事手段改变战局。此举可能加剧乌克兰危机，对欧洲安全格局产生深远影响。后续可能引发国际社会的强烈反应。",
          "keywords": [
            "俄罗斯",
            "乌克兰冲突",
            "欧洲安全",
            "军事行动"
          ],
          "category": "international",
          "importance": 90,
          "sources": [
            {
              "name": "BBC World",
              "url": "https://www.bbc.co.uk/news/articles/c2el7xpnzrpo?at_medium=RSS&at_campaign=rss"
            }
          ],
          "rank": 1
        },
        {
          "title": "美伊在约旦交火，美军士兵遭袭后美国回应",
          "titleOrig": "US and Iran trade fire after two US soldiers killed in Jordan",
          "url": "https://www.bbc.co.uk/news/articles/cgk417jp83po?at_medium=RSS&at_campaign=rss",
          "source": "BBC World",
          "sourceId": "bbc",
          "tier": "s",
          "cat": "intl",
          "region": "英国",
          "lang": "en",
          "publishedAt": "2026-07-19T13:10:57+00:00",
          "desc": "Kuwait says an electricity and water plant is on fire after the second such attack in two days. Iran says US strikes hit an under-construction nuclear power plant.",
          "hotLabel": "",
          "summary": "美军士兵在约旦遭袭，美伊双方发生冲突。",
          "analysis": "美军士兵在约旦遭袭事件可能加剧美伊紧张关系，双方在地区安全上的对立加剧。美伊冲突可能引发中东地区不稳定，对国际能源市场产生重大影响。后续可能进一步升级为直接军事对抗。",
          "keywords": [
            "美伊冲突",
            "美军士兵",
            "中东安全",
            "能源市场"
          ],
          "category": "international",
          "importance": 85,
          "sources": [
            {
              "name": "BBC World",
              "url": "https://www.bbc.co.uk/news/articles/cgk417jp83po?at_medium=RSS&at_campaign=rss"
            }
          ],
          "rank": 2
        },
        {
          "title": "俄罗斯加强对反战言论的打压，两名批评者受罚",
          "titleOrig": "One anti-war critic fined, another held as Russia clamps down on dissent",
          "url": "https://www.bbc.co.uk/news/articles/cn0n3y6ewn4o?at_medium=RSS&at_campaign=rss",
          "source": "BBC World",
          "sourceId": "bbc",
          "tier": "s",
          "cat": "intl",
          "region": "英国",
          "lang": "en",
          "publishedAt": "2026-07-17T20:00:54+00:00",
          "desc": "While Boris Nadezhdin is barred from running for parliament, blogger Ilya Remeslo is remanded in custody.",
          "hotLabel": "",
          "summary": "俄罗斯限制反战活动，两名批评者分别被禁止参选和拘留。",
          "analysis": "俄罗斯加强对反战言论的打压反映了该国政府对异见声音的严格管控。这可能与国际政治环境有关，尤其是在乌克兰危机后，俄罗斯政府试图维护其在国内和国际上的稳定。此行为可能引发国际社会的关注和批评，对俄罗斯的国内政治和国际形象产生负面影响。未来，预计俄罗斯政府可能会继续加强对言论自由的限制。",
          "keywords": [
            "俄罗斯",
            "反战",
            "言论自由",
            "打压",
            "国际关系"
          ],
          "category": "international",
          "importance": 85,
          "sources": [
            {
              "name": "BBC World",
              "url": "https://www.bbc.co.uk/news/articles/cn0n3y6ewn4o?at_medium=RSS&at_campaign=rss"
            }
          ],
          "rank": 3
        },
        {
          "title": "圣多美和普林西比紧张总统选举",
          "titleOrig": "São Tomé and Príncipe heads to polls in tense presidential election",
          "url": "https://www.theguardian.com/world/2026/jul/19/sao-tome-and-principe-presidential-election",
          "source": "The Guardian",
          "sourceId": "guardian",
          "tier": "a",
          "cat": "intl",
          "region": "英国",
          "lang": "en",
          "publishedAt": "2026-07-19T04:00:16+00:00",
          "desc": "Incumbent Carlos Vila Nova hopes to defeat his former party and secure second term as independentVoters in São Tomé and Príncipe go to the polls for a presidential election on Sunday as one of Africa’s least populous countries seeks to burnish its democratic credentials.According to the National Ele",
          "hotLabel": "",
          "summary": "圣多美和普林西比总统选举紧张，现任总统寻求连任。",
          "analysis": "圣多美和普林西比的总统选举反映了非洲小国在民主化进程中的挑战。现任总统寻求连任可能引发国内政治紧张，并影响该国的政治稳定和区域关系。后续可能包括对民主进程和国际干预的讨论。",
          "keywords": [
            "圣多美和普林西比",
            "总统选举",
            "民主化",
            "政治稳定",
            "区域关系"
          ],
          "category": "international",
          "importance": 80,
          "sources": [
            {
              "name": "The Guardian",
              "url": "https://www.theguardian.com/world/2026/jul/19/sao-tome-and-principe-presidential-election"
            }
          ],
          "rank": 4
        },
        {
          "title": "Kalshi在世界杯期间新增300万用户，预测市场借助世界杯商机",
          "titleOrig": "Kalshi adds 3 million new users as prediction market capitalizes on the World Cup",
          "url": "https://www.cnbc.com/2026/07/19/kalshi-adds-3-million-new-users-as-company-capitalizes-on-world-cup.html",
          "source": "CNBC World",
          "sourceId": "cnbc",
          "tier": "a",
          "cat": "economy",
          "region": "美国",
          "lang": "en",
          "publishedAt": "2026-07-19T12:42:30+00:00",
          "desc": "The prediction market has launched some ads featuring soccer players, as well as formed a partnership to display its brand in more places during the tournament.",
          "hotLabel": "",
          "summary": "Kalshi利用世界杯商机，用户数量激增。",
          "analysis": "预测市场通过世界杯赛事吸引大量用户，反映了体育赛事对相关产业的带动作用。Kalshi的成功可能推动预测市场进一步发展。",
          "keywords": [
            "Kalshi",
            "世界杯",
            "预测市场",
            "体育产业"
          ],
          "category": "economy",
          "importance": 75,
          "sources": [
            {
              "name": "CNBC World",
              "url": "https://www.cnbc.com/2026/07/19/kalshi-adds-3-million-new-users-as-company-capitalizes-on-world-cup.html"
            }
          ],
          "rank": 5
        },
        {
          "title": "欧盟新边境系统导致护照检查时间延长，机场负责人表示",
          "titleOrig": "New EU border system tripling time at passport control, airport boss says",
          "url": "https://www.bbc.co.uk/news/articles/ckg5gg6n9x3o?at_medium=RSS&at_campaign=rss",
          "source": "BBC World",
          "sourceId": "bbc",
          "tier": "s",
          "cat": "intl",
          "region": "英国",
          "lang": "en",
          "publishedAt": "2026-07-19T01:47:59+00:00",
          "desc": "Ryanair has also warned passengers travelling to Europe this summer to prepare for extended waits.",
          "hotLabel": "",
          "summary": "欧盟新边境系统导致护照检查时间延长，机场等待时间增加。",
          "analysis": "欧盟新边境系统的实施旨在加强边境安全，但同时也增加了旅客的等待时间。这反映了欧洲在安全与便利之间的权衡。对旅游业和跨境旅行的影响可能长期存在，同时可能促使欧盟重新评估其边境管理策略。后续可能包括对系统进行优化或调整政策以平衡安全和效率。",
          "keywords": [
            "欧盟",
            "边境安全",
            "护照检查",
            "旅行",
            "机场"
          ],
          "category": "international",
          "importance": 75,
          "sources": [
            {
              "name": "BBC World",
              "url": "https://www.bbc.co.uk/news/articles/ckg5gg6n9x3o?at_medium=RSS&at_campaign=rss"
            }
          ],
          "rank": 6
        },
        {
          "title": "德国加强对洗钱和逃税的打击",
          "titleOrig": "Germany cracks down on money laundering, tax fraud",
          "url": "https://www.dw.com/en/germany-cracks-down-on-money-laundering-tax-fraud/a-78011524?maca=en-rss-en-all-1573-rdf",
          "source": "Deutsche Welle",
          "sourceId": "dw",
          "tier": "a",
          "cat": "intl",
          "region": "德国",
          "lang": "en",
          "publishedAt": "2026-07-18T11:38:00+00:00",
          "desc": "The German government plans to crack down on tax fraud, money laundering and illegally acquired assets with more audits and stiffer penalties.",
          "hotLabel": "",
          "summary": "德国政府计划通过更多审计和严厉惩罚来打击洗钱、逃税和非法所得。",
          "analysis": "德国加强对洗钱和逃税的打击是国际反洗钱合作的一部分。这一举措可能对全球金融体系产生积极影响，提高金融交易的透明度。同时，这也有助于维护德国的金融稳定和国际形象。未来，预计欧洲其他国家也可能加强此类打击。",
          "keywords": [
            "德国",
            "洗钱",
            "逃税",
            "金融体系",
            "国际合作"
          ],
          "category": "international",
          "importance": 75,
          "sources": [
            {
              "name": "Deutsche Welle",
              "url": "https://www.dw.com/en/germany-cracks-down-on-money-laundering-tax-fraud/a-78011524?maca=en-rss-en-all-1573-rdf"
            }
          ],
          "rank": 7
        },
        {
          "title": "载有116名乘客的渡轮在圭亚那海岸沉没",
          "titleOrig": "Ferry carrying 116 passengers sinks off Guyana coast, authorities say",
          "url": "https://www.bbc.co.uk/news/articles/cm2gm99nrm7o?at_medium=RSS&at_campaign=rss",
          "source": "BBC World",
          "sourceId": "bbc",
          "tier": "s",
          "cat": "intl",
          "region": "英国",
          "lang": "en",
          "publishedAt": "2026-07-19T09:59:41+00:00",
          "desc": "The vessel capsized between Georgetown and Port Kaituma, with 53 people so far rescued.",
          "hotLabel": "",
          "summary": "圭亚那渡轮沉没，造成人员伤亡。",
          "analysis": "渡轮沉没事件反映了圭亚那海上交通的安全问题，可能对当地旅游业和民众生活造成影响。事件可能促使圭亚那政府加强海上安全监管。",
          "keywords": [
            "圭亚那",
            "渡轮沉没",
            "海上安全",
            "旅游业"
          ],
          "category": "international",
          "importance": 70,
          "sources": [
            {
              "name": "BBC World",
              "url": "https://www.bbc.co.uk/news/articles/cm2gm99nrm7o?at_medium=RSS&at_campaign=rss"
            }
          ],
          "rank": 8
        },
        {
          "title": "德国政治家因代孕儿童争议辞职",
          "titleOrig": "German politician resigns over surrogacy child controversy",
          "url": "https://www.bbc.co.uk/news/articles/cq56e9n1ddzo?at_medium=RSS&at_campaign=rss",
          "source": "BBC World",
          "sourceId": "bbc",
          "tier": "s",
          "cat": "intl",
          "region": "英国",
          "lang": "en",
          "publishedAt": "2026-07-18T15:23:31+00:00",
          "desc": "Jens Spahn faced criticism over his use of a surrogate, a ban on which he previously backed.",
          "hotLabel": "",
          "summary": "德国政治家Jens Spahn因使用代孕并支持代孕禁令而辞职。",
          "analysis": "Jens Spahn的辞职反映了代孕在德国社会中的争议性。这一事件可能引发关于家庭价值观、代孕合法性和政治道德的更广泛讨论。对德国政治的影响可能包括对家庭政策和社会价值观的重新审视。",
          "keywords": [
            "德国",
            "代孕",
            "政治家",
            "辞职",
            "家庭价值观"
          ],
          "category": "international",
          "importance": 70,
          "sources": [
            {
              "name": "BBC World",
              "url": "https://www.bbc.co.uk/news/articles/cq56e9n1ddzo?at_medium=RSS&at_campaign=rss"
            }
          ],
          "rank": 9
        },
        {
          "title": "这座沙漠城市如何应对高温死亡问题",
          "titleOrig": "What this desert city can teach the world about tackling heat deaths",
          "url": "https://www.bbc.co.uk/news/articles/cgl3lnpxy6no?at_medium=RSS&at_campaign=rss",
          "source": "BBC World",
          "sourceId": "bbc",
          "tier": "s",
          "cat": "intl",
          "region": "英国",
          "lang": "en",
          "publishedAt": "2026-07-17T23:56:08+00:00",
          "desc": "Maricopa County in Arizona has some of the hottest temperatures, but it has reduced the number of heat-related deaths.",
          "hotLabel": "",
          "summary": "亚利桑那州马里科帕县高温死亡率下降，为世界提供应对热死亡经验。",
          "analysis": "马里科帕县的成功案例表明，即使在高温频发的地区，通过有效的政策和管理措施，可以显著降低热死亡风险。这对于全球气候变化的应对具有借鉴意义，尤其是对于高温频发地区。未来，全球可能需要借鉴此类经验，以减少高温对人类健康的影响。",
          "keywords": [
            "高温",
            "热死亡",
            "气候变化",
            "政策",
            "国际经验"
          ],
          "category": "international",
          "importance": 70,
          "sources": [
            {
              "name": "BBC World",
              "url": "https://www.bbc.co.uk/news/articles/cgl3lnpxy6no?at_medium=RSS&at_campaign=rss"
            }
          ],
          "rank": 10
        },
        {
          "title": "私人飞机涌入蒙大拿，但当地人负担不起拖车公园",
          "titleOrig": "Private jets flock to Montana - but locals can't afford the trailer park",
          "url": "https://www.bbc.co.uk/news/articles/ckg92d8d40yo?at_medium=RSS&at_campaign=rss",
          "source": "BBC World",
          "sourceId": "bbc",
          "tier": "s",
          "cat": "intl",
          "region": "英国",
          "lang": "en",
          "publishedAt": "2026-07-18T23:44:04+00:00",
          "desc": "Rents in Bozeman, Montana have skyrocketed as wealthy out-of-towners flock to the city to experience the American West.",
          "hotLabel": "",
          "summary": "蒙大拿州租金飙升，因富裕的外地人涌入体验美国西部。",
          "analysis": "这一现象揭示了财富不平等和地区经济差异的问题。蒙大拿州成为富裕人士的度假地，导致当地房价和租金飙升，加剧了社会不平等。这可能引发对地区发展和经济政策改革的讨论。",
          "keywords": [
            "蒙大拿州",
            "私人飞机",
            "租金",
            "经济不平等",
            "地区发展"
          ],
          "category": "international",
          "importance": 65,
          "sources": [
            {
              "name": "BBC World",
              "url": "https://www.bbc.co.uk/news/articles/ckg92d8d40yo?at_medium=RSS&at_campaign=rss"
            }
          ],
          "rank": 11
        },
        {
          "title": "加拿大最北城市伊魁利图开通首条公交线",
          "titleOrig": "Iqaluit, Canada’s Most Northern City, Gets Its First Bus Line",
          "url": "https://www.nytimes.com/2026/07/18/world/canada/iqaluit-arctic-city-bus.html",
          "source": "NYT World",
          "sourceId": "nyt",
          "tier": "s",
          "cat": "intl",
          "region": "美国",
          "lang": "en",
          "publishedAt": "2026-07-18T09:01:07+00:00",
          "desc": "Jacinto Marques left Angola for Canada’s frozen edge. Now he’s running a bus service in Iqaluit, the largest, and only city in Canada’s Arctic.",
          "hotLabel": "",
          "summary": "安哥拉移民在加拿大北极地区城市伊魁利图开设公交服务。",
          "analysis": "伊魁利图的公交线开通是加拿大北极地区交通发展的重要里程碑。这不仅有助于提升当地居民的生活质量，也可能促进该地区的经济和社会发展。此举可能对加拿大北极地区的长期战略产生积极影响，包括资源开发和环境保护。",
          "keywords": [
            "加拿大",
            "公交",
            "北极",
            "移民",
            "经济发展"
          ],
          "category": "international",
          "importance": 65,
          "sources": [
            {
              "name": "NYT World",
              "url": "https://www.nytimes.com/2026/07/18/world/canada/iqaluit-arctic-city-bus.html"
            }
          ],
          "rank": 12
        },
        {
          "title": "以色列滑翔伞运动员试图拯救在西墙筑巢的迁徙雨燕",
          "titleOrig": "An Israeli paraglider tries to save migrating swifts that nest in the Western Wall",
          "url": "https://www.npr.org/2026/07/19/nx-s1-5870684/israel-swift-birds-jerusalem",
          "source": "NPR News",
          "sourceId": "npr",
          "tier": "a",
          "cat": "intl",
          "region": "美国",
          "lang": "en",
          "publishedAt": "2026-07-19T10:00:00+00:00",
          "desc": "Swifts have nested in Jerusalem's Western Wall since biblical times. Now one Israeli paraglider is trying to save them.",
          "hotLabel": "",
          "summary": "以色列滑翔伞运动员救助在西墙筑巢的迁徙雨燕。",
          "analysis": "该事件体现了以色列社会对自然保护的重视，同时也展示了个人在保护环境方面的努力。事件可能引发对城市生态保护的关注。",
          "keywords": [
            "以色列",
            "西墙",
            "雨燕保护",
            "生态保护"
          ],
          "category": "society",
          "importance": 60,
          "sources": [
            {
              "name": "NPR News",
              "url": "https://www.npr.org/2026/07/19/nx-s1-5870684/israel-swift-birds-jerusalem"
            }
          ],
          "rank": 13
        },
        {
          "title": "以色列为防止监狱越狱，允许鳄鱼参与安保",
          "titleOrig": "Israel clears way for crocodiles to stop prison breaks",
          "url": "https://www.dw.com/en/israel-clears-way-for-crocodiles-to-stop-prison-breaks/a-78022950?maca=en-rss-en-all-1573-rdf",
          "source": "Deutsche Welle",
          "sourceId": "dw",
          "tier": "a",
          "cat": "intl",
          "region": "德国",
          "lang": "en",
          "publishedAt": "2026-07-19T06:39:00+00:00",
          "desc": "Israel's environment minister has reclassified crocodiles so that they can now be used for security purposes. Far-right Security Minister Itamar Ben-Gvir reportedly wants them to surround a jail holding Hamas militants.",
          "hotLabel": "",
          "summary": "以色列环境部长重新分类鳄鱼，使其可用于监狱安保。",
          "analysis": "以色列的这一举措是在监狱安保方面的非传统尝试。虽然可能有效防止越狱，但也引发了对动物权益和监狱安全措施的伦理讨论。这可能影响以色列的监狱管理政策和国际形象。",
          "keywords": [
            "以色列",
            "监狱安保",
            "鳄鱼",
            "动物权益",
            "监狱管理"
          ],
          "category": "international",
          "importance": 60,
          "sources": [
            {
              "name": "Deutsche Welle",
              "url": "https://www.dw.com/en/israel-clears-way-for-crocodiles-to-stop-prison-breaks/a-78022950?maca=en-rss-en-all-1573-rdf"
            }
          ],
          "rank": 14
        },
        {
          "title": "Hungary's president signs amendment ending his own term",
          "titleOrig": "Hungary's president signs amendment ending his own term",
          "url": "https://www.dw.com/en/hungary-s-president-signs-amendment-ending-his-own-term/a-78021311?maca=en-rss-en-all-1573-rdf",
          "source": "Deutsche Welle",
          "sourceId": "dw",
          "tier": "a",
          "cat": "intl",
          "region": "德国",
          "lang": "en",
          "publishedAt": "2026-07-18T20:29:00+00:00",
          "desc": "An ally of former PM Viktor Orban has signed a constitutional amendment ending his own term as head of state. Tamas Sulyok criticized the law, while lawmakers insist he has impeded national progress by staying in office.",
          "hotLabel": "",
          "summary": "",
          "analysis": "（解读生成失败）",
          "keywords": [],
          "category": "international",
          "importance": 60,
          "sources": [
            {
              "name": "Deutsche Welle",
              "url": "https://www.dw.com/en/hungary-s-president-signs-amendment-ending-his-own-term/a-78021311?maca=en-rss-en-all-1573-rdf"
            }
          ],
          "rank": 15
        },
        {
          "title": "Norway: Huge fire destroys 100 homes, sparks evacuations",
          "titleOrig": "Norway: Huge fire destroys 100 homes, sparks evacuations",
          "url": "https://www.dw.com/en/norway-huge-fire-destroys-100-homes-sparks-evacuations/a-78019089?maca=en-rss-en-all-1573-rdf",
          "source": "Deutsche Welle",
          "sourceId": "dw",
          "tier": "a",
          "cat": "intl",
          "region": "德国",
          "lang": "en",
          "publishedAt": "2026-07-18T19:25:00+00:00",
          "desc": "Firefighters from other areas of Norway were drafted in to help tackle the blaze in the southern city of Drammen.",
          "hotLabel": "",
          "summary": "",
          "analysis": "（解读生成失败）",
          "keywords": [],
          "category": "international",
          "importance": 60,
          "sources": [
            {
              "name": "Deutsche Welle",
              "url": "https://www.dw.com/en/norway-huge-fire-destroys-100-homes-sparks-evacuations/a-78019089?maca=en-rss-en-all-1573-rdf"
            }
          ],
          "rank": 16
        },
        {
          "title": "Laos says it can't determine cause of tourist deaths linked to methanol",
          "titleOrig": "Laos says it can't determine cause of tourist deaths linked to methanol",
          "url": "https://www.bbc.co.uk/news/articles/cdx8rj99endo?at_medium=RSS&at_campaign=rss",
          "source": "BBC World",
          "sourceId": "bbc",
          "tier": "s",
          "cat": "intl",
          "region": "英国",
          "lang": "en",
          "publishedAt": "2026-07-18T11:10:20+00:00",
          "desc": "Officials say they have no evidence of poisoning over the 2024 deaths because autopsies were not conducted.",
          "hotLabel": "",
          "summary": "",
          "analysis": "（解读生成失败）",
          "keywords": [],
          "category": "international",
          "importance": 60,
          "sources": [
            {
              "name": "BBC World",
              "url": "https://www.bbc.co.uk/news/articles/cdx8rj99endo?at_medium=RSS&at_campaign=rss"
            }
          ],
          "rank": 17
        },
        {
          "title": "Indian activist on hunger strike for 20 days forcibly taken to hospital",
          "titleOrig": "Indian activist on hunger strike for 20 days forcibly taken to hospital",
          "url": "https://www.bbc.co.uk/news/articles/cjej3dxxg2do?at_medium=RSS&at_campaign=rss",
          "source": "BBC World",
          "sourceId": "bbc",
          "tier": "s",
          "cat": "intl",
          "region": "英国",
          "lang": "en",
          "publishedAt": "2026-07-18T05:58:48+00:00",
          "desc": "Cockroach Janta Party founder Abhijeet Dipke has now begun an indefinite fast in Sonam Wangchuk's place.",
          "hotLabel": "",
          "summary": "",
          "analysis": "（解读生成失败）",
          "keywords": [],
          "category": "international",
          "importance": 60,
          "sources": [
            {
              "name": "BBC World",
              "url": "https://www.bbc.co.uk/news/articles/cjej3dxxg2do?at_medium=RSS&at_campaign=rss"
            }
          ],
          "rank": 18
        },
        {
          "title": "White House defends Argentina team over Falklands banner",
          "titleOrig": "White House defends Argentina team over Falklands banner",
          "url": "https://www.bbc.co.uk/news/articles/cx2rmjk0740o?at_medium=RSS&at_campaign=rss",
          "source": "BBC World",
          "sourceId": "bbc",
          "tier": "s",
          "cat": "intl",
          "region": "英国",
          "lang": "en",
          "publishedAt": "2026-07-17T22:12:54+00:00",
          "desc": "The comments could further fuel the row over the incident, which has seen Downing Street back calls for Fifa to investigate.",
          "hotLabel": "",
          "summary": "",
          "analysis": "（解读生成失败）",
          "keywords": [],
          "category": "international",
          "importance": 60,
          "sources": [
            {
              "name": "BBC World",
              "url": "https://www.bbc.co.uk/news/articles/cx2rmjk0740o?at_medium=RSS&at_campaign=rss"
            }
          ],
          "rank": 19
        },
        {
          "title": "日本迷信影响房屋销售租赁",
          "titleOrig": "Japan's superstitions make some homes hard to sell or rent",
          "url": "https://www.dw.com/en/japan-s-superstitions-make-some-homes-hard-to-sell-or-rent/a-78005455?maca=en-rss-en-all-1573-rdf",
          "source": "Deutsche Welle",
          "sourceId": "dw",
          "tier": "a",
          "cat": "intl",
          "region": "德国",
          "lang": "en",
          "publishedAt": "2026-07-18T07:32:00+00:00",
          "desc": "Many Japanese people are reluctant to buy or rent homes where a sudden or violent death has occurred. To reassure prospective buyers and tenants, property owners are calling in \"ghost investigators.\"",
          "hotLabel": "",
          "summary": "日本家庭因迷信不愿购买或租赁发生意外死亡的房子，业主聘请“灵异调查员”以增加信心。",
          "analysis": "日本的迷信文化对房地产市场有一定影响。尽管这一现象不普遍，但它反映了日本社会中某些人对超自然现象的信仰。这可能是社会心理现象，但也可能对房地产市场的供需关系产生间接影响。未来，相关措施可能会被采取以解决此类问题。",
          "keywords": [
            "日本",
            "迷信",
            "房地产",
            "市场",
            "社会心理"
          ],
          "category": "international",
          "importance": 60,
          "sources": [
            {
              "name": "Deutsche Welle",
              "url": "https://www.dw.com/en/japan-s-superstitions-make-some-homes-hard-to-sell-or-rent/a-78005455?maca=en-rss-en-all-1573-rdf"
            }
          ],
          "rank": 20
        }
      ]
    },
    "domestic": {
      "title": "国内热点 20",
      "digest": "今日国内热点新闻反映出我国政策与社会动向的多个方面。在地质灾害风险隐患排查、城市更新中的人民民主实践等方面，体现了政府对社会稳定和民生福祉的重视。同时，国际形势的复杂多变也引起关注，如伊朗核电站事件、日本民众反对修宪等。在科技领域，具身智能的发展趋势值得关注。经济方面，电影票房的突破显示出消费市场的活力。社会事件中，干部违纪和学术不端行为受到关注。整体来看，我国在维护社会稳定、推动经济发展、应对国际挑战等方面保持积极态势，同时也需关注民生问题和国际形势变化带来的挑战。",
      "totalSelected": 20,
      "items": [
        {
          "title": "四部门部署地质灾害风险隐患巡排查",
          "titleOrig": "四部门印发通知部署做好地质灾害风险隐患巡排查 - 中国网",
          "url": "https://news.google.com/rss/articles/CBMib0FVX3lxTE9RbTJuR24xVjg3alU1NkZSdFpXdkZIMmRZWDU4a0I2R1lKaHg5cDRlWHhTSnllcjdMN0pFY2JWWUhSVVN3d3lnM3B4VjdSTG93UnBsNWxYVDBVS1BkS2pZUjFrbFptX3h6WmpZaHRFYw?oc=5",
          "source": "Google 新闻 · 中文",
          "sourceId": "gn-cn",
          "tier": "b",
          "cat": "cn",
          "region": "中国",
          "lang": "zh",
          "publishedAt": "2026-07-19T08:14:00+00:00",
          "desc": "四部门印发通知部署做好地质灾害风险隐患巡排查 中国网散布“鞭炮引发彭水山体崩塌”，苏某某（女，29岁）、李某某（女，24岁）被查处 新浪财经应对重庆地灾处置、开展全国隐患排查——自然资源部有关负责人介绍当前地灾防御工作 央视网多部门紧急通知：巡查排查地质灾害风险隐患 观察者凤凰晚报丨重庆彭水山体崩塌的“预警者” 凤凰网",
          "hotLabel": "",
          "summary": "四部门联合发布地质灾害风险隐患巡排查通知。",
          "analysis": "此新闻显示了中国政府对于地质灾害防范的高度重视。通过多部门联合巡排查，旨在降低地质灾害风险，保护人民生命财产安全。这一举措体现了中国政府在自然灾害防治方面的决心和力度，对提高国家应急管理能力具有重要意义。后续可能看到地质灾害防治工作的加强和改进。关键词：地质灾害，风险隐患，巡排查，应急管理，政策力度。分类：society。重要性：90。",
          "keywords": [
            "地质灾害",
            "风险隐患",
            "巡排查",
            "应急管理",
            "政策力度"
          ],
          "category": "society",
          "importance": 90,
          "sources": [
            {
              "name": "Google 新闻 · 中文",
              "url": "https://news.google.com/rss/articles/CBMib0FVX3lxTE9RbTJuR24xVjg3alU1NkZSdFpXdkZIMmRZWDU4a0I2R1lKaHg5cDRlWHhTSnllcjdMN0pFY2JWWUhSVVN3d3lnM3B4VjdSTG93UnBsNWxYVDBVS1BkS2pZUjFrbFptX3h6WmpZaHRFYw?oc=5"
            }
          ],
          "rank": 1
        },
        {
          "title": "城市更新中的全过程人民民主：从“三问于民”看",
          "titleOrig": "一见·从“三问于民”看城市更新中的全过程人民民主 - chinanews.com.cn",
          "url": "https://news.google.com/rss/articles/CBMiaEFVX3lxTE9TVy03cU5VeHhFMUNXZHRMTFdxOG1YTGZLNlhyRHdldi1XWWdfQV85SmUzeDFld2Y2U3I4eFJEZ3B5aWhSaU4wZnE3N3F6WUFnOFB6cVFsa29iVS1vbElsd1o4ZHpDaWF6?oc=5",
          "source": "Google 新闻 · 中文",
          "sourceId": "gn-cn",
          "tier": "b",
          "cat": "cn",
          "region": "中国",
          "lang": "zh",
          "publishedAt": "2026-07-19T07:47:20+00:00",
          "desc": "一见·从“三问于民”看城市更新中的全过程人民民主 chinanews.com.cn在Google 新闻上查看更多头条新闻和观点",
          "hotLabel": "",
          "summary": "分析城市更新过程中的民主参与机制。",
          "analysis": "此新闻反映了城市更新过程中，政府通过“三问于民”的方式，强调全过程人民民主的重要性。这体现了中国政府在城市规划和发展中，注重听取民意，增强公众参与，以实现更加民主、和谐的城市发展。这一政策意图旨在提升公民的参与感和满意度，同时促进社会治理的现代化。后续可能看到更多城市更新项目采用类似民主参与机制，以改善民生和提高城市治理水平。关键词：城市更新，全过程人民民主，公民参与，社会治理。分类：society。重要性：85。",
          "keywords": [
            "城市更新",
            "全过程人民民主",
            "公民参与",
            "社会治理",
            "政策意图"
          ],
          "category": "society",
          "importance": 85,
          "sources": [
            {
              "name": "Google 新闻 · 中文",
              "url": "https://news.google.com/rss/articles/CBMiaEFVX3lxTE9TVy03cU5VeHhFMUNXZHRMTFdxOG1YTGZLNlhyRHdldi1XWWdfQV85SmUzeDFld2Y2U3I4eFJEZ3B5aWhSaU4wZnE3N3F6WUFnOFB6cVFsa29iVS1vbElsd1o4ZHpDaWF6?oc=5"
            }
          ],
          "rank": 2
        },
        {
          "title": "伊朗谴责美国对在建核电站发动“恐怖袭击”",
          "titleOrig": "伊朗谴责美国对在建核电站发动“恐怖袭击” - chinanews.com.cn",
          "url": "https://news.google.com/rss/articles/CBMiaEFVX3lxTE5Kczc1ZElXemwxa1U3NS0zM2hGLVFVQldZTXVjdFN5YzRNRDcwMkRkR0E3c2lodnRhWURrM3JqRUtHQzRGWkw0OTJfUm0xdXM4cjJYSXJSVDNwbXBtVS1odUFKdnB3S1ZZ?oc=5",
          "source": "Google 新闻 · 中文",
          "sourceId": "gn-cn",
          "tier": "b",
          "cat": "cn",
          "region": "中国",
          "lang": "zh",
          "publishedAt": "2026-07-19T11:22:39+00:00",
          "desc": "伊朗谴责美国对在建核电站发动“恐怖袭击” chinanews.com.cn在Google 新闻上查看更多头条新闻和观点",
          "hotLabel": "",
          "summary": "伊朗指责美国袭击其核电站",
          "analysis": "伊朗与美国之间的紧张关系再次升级，此次事件可能加剧地区不稳定，影响中东地区的和平与安全。对伊朗而言，这可能是其寻求国际支持以对抗美国制裁的策略。对国际社会来说，这可能引发对核安全的关注和担忧。后续可能包括国际社会的反应和伊朗的报复行动。",
          "keywords": [
            "伊朗",
            "美国",
            "核电站",
            "恐怖袭击",
            "国际关系"
          ],
          "category": "international",
          "importance": 85,
          "sources": [
            {
              "name": "Google 新闻 · 中文",
              "url": "https://news.google.com/rss/articles/CBMiaEFVX3lxTE5Kczc1ZElXemwxa1U3NS0zM2hGLVFVQldZTXVjdFN5YzRNRDcwMkRkR0E3c2lodnRhWURrM3JqRUtHQzRGWkw0OTJfUm0xdXM4cjJYSXJSVDNwbXBtVS1odUFKdnB3S1ZZ?oc=5"
            }
          ],
          "rank": 3
        },
        {
          "title": "英国将敬业集团旗下英钢国有化",
          "titleOrig": "",
          "url": "https://www.zhihu.com/search?q=%E8%8B%B1%E5%9B%BD%E5%B0%86%E6%95%AC%E4%B8%9A%E9%9B%86%E5%9B%A2%E6%97%97%E4%B8%8B%E8%8B%B1%E9%92%A2%E5%9B%BD%E6%9C%89%E5%8C%96",
          "source": "知乎热榜",
          "sourceId": "zhihu",
          "tier": "c",
          "cat": "cn",
          "region": "中国",
          "lang": "zh",
          "publishedAt": null,
          "desc": "",
          "hotLabel": "",
          "summary": "英国政府决定将敬业集团旗下的英钢国有化",
          "analysis": "这一决策反映了英国政府对国家经济安全的重视，以及对关键行业控制的加强。对于英钢而言，国有化可能带来政策支持和资金注入，但也可能影响其市场竞争力。对于英国经济而言，这一事件可能影响其私有化和市场化改革的方向。后续可能引发关于国有化与私有化、经济政策等方面的讨论。",
          "keywords": [
            "英国",
            "敬业集团",
            "英钢",
            "国有化",
            "经济政策"
          ],
          "category": "international",
          "importance": 85,
          "sources": [
            {
              "name": "知乎热榜",
              "url": "https://www.zhihu.com/search?q=%E8%8B%B1%E5%9B%BD%E5%B0%86%E6%95%AC%E4%B8%9A%E9%9B%86%E5%9B%A2%E6%97%97%E4%B8%8B%E8%8B%B1%E9%92%A2%E5%9B%BD%E6%9C%89%E5%8C%96"
            }
          ],
          "rank": 4
        },
        {
          "title": "李希在重庆调研强调深入学习贯彻习近平党建思想",
          "titleOrig": "李希在重庆调研时强调深入学习贯彻习近平党建思想以更高标准更实举措做好纪检监察各项工作 - hebcdi.gov.cn",
          "url": "https://news.google.com/rss/articles/CBMiZkFVX3lxTE1iMExqTy1zQWY3LVp4VkFDZ3RVekprYWN6ZjZZMGlBVEdsQjU2MWhnNzFtUW9PaWhfbUJxOG9nU3hUZHNrelRibTh6bXUwTjNRaURkTDVnRHFzMmZxT2NLc0ZBVk9WUQ?oc=5",
          "source": "Google 新闻 · 中文",
          "sourceId": "gn-cn",
          "tier": "b",
          "cat": "cn",
          "region": "中国",
          "lang": "zh",
          "publishedAt": "2026-07-19T11:57:34+00:00",
          "desc": "李希在重庆调研时强调深入学习贯彻习近平党建思想以更高标准更实举措做好纪检监察各项工作 hebcdi.gov.cn",
          "hotLabel": "",
          "summary": "李希在重庆调研强调深入学习贯彻习近平党建思想。",
          "analysis": "此新闻表明中国政府在党建方面的高度重视。李希在重庆的调研强调了习近平党建思想的重要性，并提出了更高标准、更实举措的要求。这反映了中国共产党在加强自身建设、提高执政能力方面的决心。后续可能看到党建工作的进一步加强和改进。关键词：习近平党建思想，党建，执政能力，自我建设，政策要求。分类：domestic。重要性：80。",
          "keywords": [
            "习近平党建思想",
            "党建",
            "执政能力",
            "自我建设",
            "政策要求"
          ],
          "category": "domestic",
          "importance": 80,
          "sources": [
            {
              "name": "Google 新闻 · 中文",
              "url": "https://news.google.com/rss/articles/CBMiZkFVX3lxTE1iMExqTy1zQWY3LVp4VkFDZ3RVekprYWN6ZjZZMGlBVEdsQjU2MWhnNzFtUW9PaWhfbUJxOG9nU3hUZHNrelRibTh6bXUwTjNRaURkTDVnRHFzMmZxT2NLc0ZBVk9WUQ?oc=5"
            }
          ],
          "rank": 5
        },
        {
          "title": "WAIC 2026观察：具身智能的“去表演化”之年",
          "titleOrig": "WAIC 2026观察：具身智能的“去表演化”之年 - cb.com.cn",
          "url": "https://news.google.com/rss/articles/CBMiYkFVX3lxTE9uM09LblFuMXdqUU1KSWRPUFR6YWxPREtIMHJjQ1NsUGlJOEMtSEhVR3pjRHNOUDV4ODFZU28wR1lmRG9uQ213Z3A4NkVsUGgwVDhPN0FQRDNkSkdubklSTF9R?oc=5",
          "source": "Google 新闻 · 中文",
          "sourceId": "gn-cn",
          "tier": "b",
          "cat": "cn",
          "region": "中国",
          "lang": "zh",
          "publishedAt": "2026-07-19T10:14:00+00:00",
          "desc": "WAIC 2026观察：具身智能的“去表演化”之年 cb.com.cn人工智能引领产业变革思客会现场 新华网300+机器人参展物理AI为何站上WAIC的\"C位\"？|世界人工智能大会|具身智能|数据|模型|训练_手机新浪网 新浪财经中国科学院院士：三大需求倒逼算力从地面走向太空 观察者落地一地一策赋能方案 北电数智 WAIC 专题论坛解锁民生 AI 价值 驱动之家",
          "hotLabel": "",
          "summary": "WAIC 2026关注具身智能去表演化",
          "analysis": "具身智能的发展标志着人工智能技术的新阶段，可能对各行各业产生深远影响。对国内而言，这预示着人工智能产业的新机遇和挑战。对国际社会来说，这可能成为全球科技竞争的新焦点。",
          "keywords": [
            "人工智能",
            "具身智能",
            "科技发展",
            "产业变革",
            "国际竞争"
          ],
          "category": "tech",
          "importance": 80,
          "sources": [
            {
              "name": "Google 新闻 · 中文",
              "url": "https://news.google.com/rss/articles/CBMiYkFVX3lxTE9uM09LblFuMXdqUU1KSWRPUFR6YWxPREtIMHJjQ1NsUGlJOEMtSEhVR3pjRHNOUDV4ODFZU28wR1lmRG9uQ213Z3A4NkVsUGgwVDhPN0FQRDNkSkdubklSTF9R?oc=5"
            }
          ],
          "rank": 6
        },
        {
          "title": "80后干部徐刘蔚被查",
          "titleOrig": "曾硬刚王健林的80后干部徐刘蔚被查",
          "url": "https://www.zhihu.com/search?q=%E6%9B%BE%E7%A1%AC%E5%88%9A%E7%8E%8B%E5%81%A5%E6%9E%97%E7%9A%8480%E5%90%8E%E5%B9%B2%E9%83%A8%E5%BE%90%E5%88%98%E8%94%9A%E8%A2%AB%E6%9F%A5",
          "source": "知乎热榜",
          "sourceId": "zhihu",
          "tier": "c",
          "cat": "cn",
          "region": "中国",
          "lang": "zh",
          "publishedAt": null,
          "desc": "",
          "hotLabel": "#1",
          "summary": "80后干部徐刘蔚因违纪被查。",
          "analysis": "徐刘蔚事件反映了反腐败斗争的持续性和严肃性。近年来，中国政府不断加强对腐败行为的打击，特别是对年轻干部的监督。这一事件可能对政府内部的廉洁建设产生积极影响，提高公众对政府反腐力度的信心。后续可能引发对干部选拔任用制度的讨论和改革。",
          "keywords": [
            "反腐",
            "干部",
            "违纪",
            "监督",
            "政府"
          ],
          "category": "society",
          "importance": 80,
          "sources": [
            {
              "name": "知乎热榜",
              "url": "https://www.zhihu.com/search?q=%E6%9B%BE%E7%A1%AC%E5%88%9A%E7%8E%8B%E5%81%A5%E6%9E%97%E7%9A%8480%E5%90%8E%E5%B9%B2%E9%83%A8%E5%BE%90%E5%88%98%E8%94%9A%E8%A2%AB%E6%9F%A5"
            }
          ],
          "rank": 7
        },
        {
          "title": "莫言之女管笑笑被爆论文抄袭",
          "titleOrig": "",
          "url": "https://www.zhihu.com/search?q=%E8%8E%AB%E8%A8%80%E4%B9%8B%E5%A5%B3%E7%AE%A1%E7%AC%91%E7%AC%91%E8%A2%AB%E7%88%86%E8%AE%BA%E6%96%87%E6%8A%84%E8%A2%AD",
          "source": "知乎热榜",
          "sourceId": "zhihu",
          "tier": "c",
          "cat": "cn",
          "region": "中国",
          "lang": "zh",
          "publishedAt": null,
          "desc": "",
          "hotLabel": "",
          "summary": "莫言之女管笑笑论文抄袭事件被曝光",
          "analysis": "此事件凸显了学术诚信的重要性，对学术界和社会风气有警示作用。对于莫言家族而言，这一事件可能影响其声誉。对于学术界而言，它强调了学术规范和学术道德的必要性。后续可能引发关于学术诚信和论文审查的讨论。",
          "keywords": [
            "莫言",
            "抄袭",
            "学术诚信",
            "论文",
            "学术界"
          ],
          "category": "society",
          "importance": 80,
          "sources": [
            {
              "name": "知乎热榜",
              "url": "https://www.zhihu.com/search?q=%E8%8E%AB%E8%A8%80%E4%B9%8B%E5%A5%B3%E7%AE%A1%E7%AC%91%E7%AC%91%E8%A2%AB%E7%88%86%E8%AE%BA%E6%96%87%E6%8A%84%E8%A2%AD"
            }
          ],
          "rank": 8
        },
        {
          "title": "泰国总理出席中泰投资与经济论坛并为成都总领事馆投资处揭牌",
          "titleOrig": "泰国总理阿努廷出席中泰投资与经济论坛并为泰王国驻成都总领事馆投资处揭牌 - 中国日报网",
          "url": "https://news.google.com/rss/articles/CBMie0FVX3lxTE04UnZJd0hDZTY1bUdVY3FCMXBYanNyNXpFdGpvQ1VDNk41YkcxZFhRTHRTMG5qeGhXbG1oV2lJd0drZ2U5cklOWV8zbEtrMVYxVEx0emJqbXduY09TVTlUV2RMdzZEUkxINlR1Q0FpeHI5dl9IdEJMSk9pTQ?oc=5",
          "source": "Google 新闻 · 中文",
          "sourceId": "gn-cn",
          "tier": "b",
          "cat": "cn",
          "region": "中国",
          "lang": "zh",
          "publishedAt": "2026-07-19T08:11:09+00:00",
          "desc": "泰国总理阿努廷出席中泰投资与经济论坛并为泰王国驻成都总领事馆投资处揭牌 中国日报网洽谈桌前面对面，中泰企业聊了些什么？ 新浪财经“中泰一家亲”：“泰”多精彩 历久弥新 中国经济网泰国总理用中文发文 观察者泰国总理阿努廷抵达北京 新京报",
          "hotLabel": "",
          "summary": "泰国总理出席中泰投资与经济论坛并为成都总领事馆投资处揭牌。",
          "analysis": "此新闻标志着中泰两国在投资和经济领域的深化合作。泰国总理的出席和成都总领事馆投资处的揭牌，体现了中泰两国在“一带一路”倡议下的紧密合作关系。这对两国经济发展和区域经济一体化具有重要意义。后续可能看到更多中泰合作项目的推进。关键词：中泰合作，投资论坛，一带一路，经济一体化，区域合作。分类：international。重要性：75。",
          "keywords": [
            "中泰合作",
            "投资论坛",
            "一带一路",
            "经济一体化",
            "区域合作"
          ],
          "category": "international",
          "importance": 75,
          "sources": [
            {
              "name": "Google 新闻 · 中文",
              "url": "https://news.google.com/rss/articles/CBMie0FVX3lxTE04UnZJd0hDZTY1bUdVY3FCMXBYanNyNXpFdGpvQ1VDNk41YkcxZFhRTHRTMG5qeGhXbG1oV2lJd0drZ2U5cklOWV8zbEtrMVYxVEx0emJqbXduY09TVTlUV2RMdzZEUkxINlR1Q0FpeHI5dl9IdEJMSk9pTQ?oc=5"
            }
          ],
          "rank": 9
        },
        {
          "title": "日本民众集会反对修宪呼吁珍视和平宪法",
          "titleOrig": "视频丨日本民众集会反对修宪呼吁珍视和平宪法_国际时讯 - 大众网",
          "url": "https://news.google.com/rss/articles/CBMigAFBVV95cUxPaElvQ1RZbXhBa3dxQXFycTd1cm95SDA4dTE4N2RwcFFMcmFFMk9adzVZRXNrS1Y3c2ptYktLbEd3Z0RySnFGZXNsbGtUejVySHB0NmYxWjZhQ2RXbDB0RmU1eVk2ZEJJT3RJTVRWWTdyMXE1dndOTTJNSE5WcnJTSQ?oc=5",
          "source": "Google 新闻 · 中文",
          "sourceId": "gn-cn",
          "tier": "b",
          "cat": "cn",
          "region": "中国",
          "lang": "zh",
          "publishedAt": "2026-07-19T09:11:00+00:00",
          "desc": "视频丨日本民众集会反对修宪呼吁珍视和平宪法_国际时讯 大众网日本各界人士反对修宪呼吁守护和平宪法--国际 人民网日本农民团体反对政府增加防卫费 china.zjol.com.cn数万民众齐聚东京抗议高市政府，天价防卫预算掀起全民反战浪潮 #海外突发 #真实海外社会 腾讯新闻当不成首相了？日本爆发抗议，高市早苗或被逼宫，美国警告日本 网易新闻客户端",
          "hotLabel": "",
          "summary": "日本民众集会反对修宪",
          "analysis": "日本民众反对修宪反映了公众对军事扩张的担忧，可能影响日本政治走向。对日本而言，这可能是维护和平宪法和民主制度的信号。对国际社会来说，这关乎地区和平与稳定。",
          "keywords": [
            "日本",
            "修宪",
            "和平宪法",
            "民主",
            "国际关系"
          ],
          "category": "international",
          "importance": 75,
          "sources": [
            {
              "name": "Google 新闻 · 中文",
              "url": "https://news.google.com/rss/articles/CBMigAFBVV95cUxPaElvQ1RZbXhBa3dxQXFycTd1cm95SDA4dTE4N2RwcFFMcmFFMk9adzVZRXNrS1Y3c2ptYktLbEd3Z0RySnFGZXNsbGtUejVySHB0NmYxWjZhQ2RXbDB0RmU1eVk2ZEJJT3RJTVRWWTdyMXE1dndOTTJNSE5WcnJTSQ?oc=5"
            }
          ],
          "rank": 10
        },
        {
          "title": "2026年电影票房破200亿，暑期档达40亿",
          "titleOrig": "2026年电影票房破200亿，暑期档达40亿 - DoNews",
          "url": "https://news.google.com/rss/articles/CBMiXkFVX3lxTE1SanJucVdkSmt0dzN4Q1U3cUU3dDctQ2pZMFVHVEI2Qm13SkY3T1J1MHJySHRJcEJkbFVxOXFLVEdvd2oxem1wLThmYnJWV0ZDTzhqYll5NlBhNndlQVE?oc=5",
          "source": "Google 新闻 · 中文",
          "sourceId": "gn-cn",
          "tier": "b",
          "cat": "cn",
          "region": "中国",
          "lang": "zh",
          "publishedAt": "2026-07-19T06:04:03+00:00",
          "desc": "2026年电影票房破200亿，暑期档达40亿 DoNews2026年度电影总票房突破200亿！ 新浪财经2026年中国电影年度票房突破200亿元 新浪财经《功夫女足》上映8天票房近11亿，豆瓣6.5分却冲击30亿 虎嗅网2026年全国电影票房破200亿！广东稳居“第一票仓” 搜狐网",
          "hotLabel": "",
          "summary": "2026年电影票房突破200亿",
          "analysis": "电影票房的增长反映了国内娱乐市场的繁荣，对电影产业和经济增长有积极影响。对国内而言，这可能是文化产业发展和消费升级的体现。对国际电影市场来说，这可能增加中国市场的吸引力。",
          "keywords": [
            "电影票房",
            "娱乐市场",
            "文化产业",
            "经济增长",
            "消费升级"
          ],
          "category": "economy",
          "importance": 75,
          "sources": [
            {
              "name": "Google 新闻 · 中文",
              "url": "https://news.google.com/rss/articles/CBMiXkFVX3lxTE1SanJucVdkSmt0dzN4Q1U3cUU3dDctQ2pZMFVHVEI2Qm13SkY3T1J1MHJySHRJcEJkbFVxOXFLVEdvd2oxem1wLThmYnJWV0ZDTzhqYll5NlBhNndlQVE?oc=5"
            }
          ],
          "rank": 11
        },
        {
          "title": "日本护士将排泄物混入患者输液",
          "titleOrig": "",
          "url": "https://www.zhihu.com/search?q=%E6%97%A5%E6%9C%AC%E6%8A%A4%E5%A3%AB%E5%B0%86%E6%8E%92%E6%B3%84%E7%89%A9%E6%B7%B7%E5%85%A5%E6%82%A3%E8%80%85%E8%BE%93%E6%B6%B2",
          "source": "知乎热榜",
          "sourceId": "zhihu",
          "tier": "c",
          "cat": "cn",
          "region": "中国",
          "lang": "zh",
          "publishedAt": null,
          "desc": "",
          "hotLabel": "",
          "summary": "日本护士将排泄物混入患者输液。",
          "analysis": "该事件揭示了医疗安全问题的严重性。这要求各国加强医疗监管，提高医护人员职业素养。对于中国而言，可能促使国内医疗机构加强内部管理，提升医疗服务质量。",
          "keywords": [
            "医疗安全",
            "日本护士",
            "排泄物",
            "医疗监管",
            "职业素养"
          ],
          "category": "international",
          "importance": 75,
          "sources": [
            {
              "name": "知乎热榜",
              "url": "https://www.zhihu.com/search?q=%E6%97%A5%E6%9C%AC%E6%8A%A4%E5%A3%AB%E5%B0%86%E6%8E%92%E6%B3%84%E7%89%A9%E6%B7%B7%E5%85%A5%E6%82%A3%E8%80%85%E8%BE%93%E6%B6%B2"
            }
          ],
          "rank": 12
        },
        {
          "title": "西班牙阿根廷谁能夺冠",
          "titleOrig": "",
          "url": "https://www.zhihu.com/search?q=%E8%A5%BF%E7%8F%AD%E7%89%99%E9%98%BF%E6%A0%B9%E5%BB%B7%E8%B0%81%E8%83%BD%E5%A4%BA%E5%86%A0",
          "source": "知乎热榜",
          "sourceId": "zhihu",
          "tier": "c",
          "cat": "cn",
          "region": "中国",
          "lang": "zh",
          "publishedAt": null,
          "desc": "",
          "hotLabel": "",
          "summary": "讨论西班牙和阿根廷在世界杯中的夺冠可能性",
          "analysis": "这一讨论反映了国际体育赛事对全球观众的吸引力，同时也体现了足球运动在各国社会中的地位。对于西班牙和阿根廷两国而言，夺冠不仅是对足球实力的认可，也是国家形象和文化输出的体现。后续可能引发关于足球战略和战术的深入分析。",
          "keywords": [
            "世界杯",
            "足球",
            "西班牙",
            "阿根廷",
            "夺冠"
          ],
          "category": "international",
          "importance": 75,
          "sources": [
            {
              "name": "知乎热榜",
              "url": "https://www.zhihu.com/search?q=%E8%A5%BF%E7%8F%AD%E7%89%99%E9%98%BF%E6%A0%B9%E5%BB%B7%E8%B0%81%E8%83%BD%E5%A4%BA%E5%86%A0"
            }
          ],
          "rank": 13
        },
        {
          "title": "北京大风蓝色预警：大部分地区有7级大风",
          "titleOrig": "北京大风蓝色预警：大部分地区有7级大风 4区局地阵风可超8级 - 天气网",
          "url": "https://news.google.com/rss/articles/CBMiXEFVX3lxTFBVMDFCZm9hdXppQ2pVTlNDQzlLWEp3UUlVZHBsbXVvdkxIY25lMXRsZnRNV0tiX0VwM080OUV3WERiU0JNd0RVQnRKUWdZYTNjQ1B2VXE1QmJOLXUy?oc=5",
          "source": "Google 新闻 · 中文",
          "sourceId": "gn-cn",
          "tier": "b",
          "cat": "cn",
          "region": "中国",
          "lang": "zh",
          "publishedAt": "2026-07-19T11:57:04+00:00",
          "desc": "北京大风蓝色预警：大部分地区有7级大风 4区局地阵风可超8级 天气网今天午后至傍晚，北京有雷阵雨！下周最高气温34℃，体感闷热 新浪财经北京发布雷电黄色预警 伴有强风冰雹 中华网【受权发布】北京7月19日16时30分发布雷电黄色预警 凤凰网北京今日雷雨分散 明日起进入“七下八上”主汛期关键时段 中国日报网",
          "hotLabel": "",
          "summary": "北京发布大风蓝色预警，大部分地区有7级大风。",
          "analysis": "此新闻反映了北京地区大风天气的紧急情况。大风蓝色预警的发布，提醒公众注意安全，并采取相应的防范措施。这体现了中国政府在自然灾害预警和应急响应方面的能力。后续可能看到相关部门对大风天气的应对措施和恢复工作。关键词：大风预警，自然灾害，应急响应，安全防范，政策响应。分类：society。重要性：70。",
          "keywords": [
            "大风预警",
            "自然灾害",
            "应急响应",
            "安全防范",
            "政策响应"
          ],
          "category": "society",
          "importance": 70,
          "sources": [
            {
              "name": "Google 新闻 · 中文",
              "url": "https://news.google.com/rss/articles/CBMiXEFVX3lxTFBVMDFCZm9hdXppQ2pVTlNDQzlLWEp3UUlVZHBsbXVvdkxIY25lMXRsZnRNV0tiX0VwM080OUV3WERiU0JNd0RVQnRKUWdZYTNjQ1B2VXE1QmJOLXUy?oc=5"
            }
          ],
          "rank": 14
        },
        {
          "title": "圭亚那一艘渡轮倾覆 8人已获救",
          "titleOrig": "圭亚那一艘渡轮倾覆 8人已获救 - 新华网客户端",
          "url": "https://news.google.com/rss/articles/CBMimgFBVV95cUxQNmlQZkFqWktUcFU1ZGRYWGVraUNmUnRBTnliaVRQZWQ1UTJWeW9ueUZTRU1qdEtRemxjZE5qSXVZcmVUelFfM1ZfRHd4UDJoUHhtczlEby0zRm1Ob2dtYmdjM3h2MmgxeFVxTFlIWFlOWGQ3ZWdXWUgzLW9oMEphVzhrWGpJdVFEbmFxOEJXNjZmN2pWZ1U5UldR?oc=5",
          "source": "Google 新闻 · 中文",
          "sourceId": "gn-cn",
          "tier": "b",
          "cat": "cn",
          "region": "中国",
          "lang": "zh",
          "publishedAt": "2026-07-19T10:42:02+00:00",
          "desc": "圭亚那一艘渡轮倾覆 8人已获救 新华网客户端圭亚那一艘载有116人的渡轮倾覆 已有53人获救 中国日报网圭亚那一艘载有116人的渡轮倾覆 新浪财经圭亚那渡轮翻船逾50人获救 TDM圭亚那一艘载有116人的渡轮倾覆 目前有8人获救 新京报",
          "hotLabel": "",
          "summary": "圭亚那渡轮倾覆，8人获救",
          "analysis": "此次渡轮事故反映了圭亚那基础设施的脆弱性，可能引发对该国水上交通工具安全的关注。对圭亚那而言，这可能是提高水上安全标准的契机。对国际社会来说，此类事件提醒了海上安全的重要性。",
          "keywords": [
            "圭亚那",
            "渡轮倾覆",
            "安全",
            "基础设施",
            "国际援助"
          ],
          "category": "society",
          "importance": 70,
          "sources": [
            {
              "name": "Google 新闻 · 中文",
              "url": "https://news.google.com/rss/articles/CBMimgFBVV95cUxQNmlQZkFqWktUcFU1ZGRYWGVraUNmUnRBTnliaVRQZWQ1UTJWeW9ueUZTRU1qdEtRemxjZE5qSXVZcmVUelFfM1ZfRHd4UDJoUHhtczlEby0zRm1Ob2dtYmdjM3h2MmgxeFVxTFlIWFlOWGQ3ZWdXWUgzLW9oMEphVzhrWGpJdVFEbmFxOEJXNjZmN2pWZ1U5UldR?oc=5"
            }
          ],
          "rank": 15
        },
        {
          "title": "重庆彭水发生山体崩塌",
          "titleOrig": "",
          "url": "https://www.zhihu.com/search?q=%E9%87%8D%E5%BA%86%E5%BD%AD%E6%B0%B4%E5%8F%91%E7%94%9F%E5%B1%B1%E4%BD%93%E5%B4%A9%E5%A1%8C",
          "source": "知乎热榜",
          "sourceId": "zhihu",
          "tier": "c",
          "cat": "cn",
          "region": "中国",
          "lang": "zh",
          "publishedAt": null,
          "desc": "",
          "hotLabel": "#2",
          "summary": "重庆彭水县发生山体崩塌。",
          "analysis": "山体崩塌事件反映了自然灾害的不可预测性和破坏力。这要求政府在灾害预防和应急响应方面加强能力建设。同时，事件可能促使地方政府对地质安全进行更严格的检查和监管，以减少类似事件的发生。",
          "keywords": [
            "山体崩塌",
            "自然灾害",
            "地质安全",
            "政府",
            "应急响应"
          ],
          "category": "society",
          "importance": 70,
          "sources": [
            {
              "name": "知乎热榜",
              "url": "https://www.zhihu.com/search?q=%E9%87%8D%E5%BA%86%E5%BD%AD%E6%B0%B4%E5%8F%91%E7%94%9F%E5%B1%B1%E4%BD%93%E5%B4%A9%E5%A1%8C"
            }
          ],
          "rank": 16
        },
        {
          "title": "阿根廷2-1英格兰",
          "titleOrig": "阿根廷 2-1 英格兰",
          "url": "https://www.zhihu.com/search?q=%E9%98%BF%E6%A0%B9%E5%BB%B7%202-1%20%E8%8B%B1%E6%A0%BC%E5%85%B0",
          "source": "知乎热榜",
          "sourceId": "zhihu",
          "tier": "c",
          "cat": "cn",
          "region": "中国",
          "lang": "zh",
          "publishedAt": null,
          "desc": "",
          "hotLabel": "",
          "summary": "阿根廷在世界杯比赛中击败英格兰",
          "analysis": "此次比赛体现了足球运动的竞技性和不确定性，对阿根廷国内足球运动的发展有积极推动作用。同时，作为国际事件，它也反映了国际体育赛事对各国社会文化的影响。后续可能引发更多关于足球运动和体育精神的社会讨论。",
          "keywords": [
            "世界杯",
            "足球",
            "阿根廷",
            "英格兰",
            "体育赛事"
          ],
          "category": "international",
          "importance": 70,
          "sources": [
            {
              "name": "知乎热榜",
              "url": "https://www.zhihu.com/search?q=%E9%98%BF%E6%A0%B9%E5%BB%B7%202-1%20%E8%8B%B1%E6%A0%BC%E5%85%B0"
            }
          ],
          "rank": 17
        },
        {
          "title": "重庆彭水大批骑手坚守救援一线",
          "titleOrig": "",
          "url": "https://www.zhihu.com/search?q=%E9%87%8D%E5%BA%86%E5%BD%AD%E6%B0%B4%E5%A4%A7%E6%89%B9%E9%AA%91%E6%89%8B%E5%9D%9A%E5%AE%88%E6%95%91%E6%8F%B4%E4%B8%80%E7%BA%BF",
          "source": "知乎热榜",
          "sourceId": "zhihu",
          "tier": "c",
          "cat": "cn",
          "region": "中国",
          "lang": "zh",
          "publishedAt": null,
          "desc": "",
          "hotLabel": "",
          "summary": "重庆彭水大批骑手参与救援。",
          "analysis": "骑手参与救援体现了社会力量的积极参与和应急响应能力的提升。这有助于提高政府在灾害救援中的效率，同时也展示了社会团结和互助的精神。后续可能促进政府与社会力量在应急管理体系上的合作。",
          "keywords": [
            "救援",
            "骑手",
            "社会力量",
            "灾害",
            "应急管理体系"
          ],
          "category": "society",
          "importance": 65,
          "sources": [
            {
              "name": "知乎热榜",
              "url": "https://www.zhihu.com/search?q=%E9%87%8D%E5%BA%86%E5%BD%AD%E6%B0%B4%E5%A4%A7%E6%89%B9%E9%AA%91%E6%89%8B%E5%9D%9A%E5%AE%88%E6%95%91%E6%8F%B4%E4%B8%80%E7%BA%BF"
            }
          ],
          "rank": 18
        },
        {
          "title": "邹市明夫妇2亿理财亏损始末",
          "titleOrig": "",
          "url": "https://www.zhihu.com/search?q=%E9%82%B9%E5%B8%82%E6%98%8E%E5%A4%AB%E5%A6%872%E4%BA%BF%E7%90%86%E8%B4%A2%E4%BA%8F%E6%8D%9F%E5%A7%8B%E6%9C%AB",
          "source": "知乎热榜",
          "sourceId": "zhihu",
          "tier": "c",
          "cat": "cn",
          "region": "中国",
          "lang": "zh",
          "publishedAt": null,
          "desc": "",
          "hotLabel": "",
          "summary": "邹市明夫妇理财亏损事件经过曝光",
          "analysis": "此事件揭示了名人理财风险和公众对名人财富管理的关注。对于公众而言，它反映了理财市场的复杂性和风险。对于邹市明夫妇而言，这一事件可能影响其个人形象和财务状况。后续可能引发关于理财教育和风险管理的讨论。",
          "keywords": [
            "邹市明",
            "理财",
            "亏损",
            "名人",
            "风险管理"
          ],
          "category": "society",
          "importance": 65,
          "sources": [
            {
              "name": "知乎热榜",
              "url": "https://www.zhihu.com/search?q=%E9%82%B9%E5%B8%82%E6%98%8E%E5%A4%AB%E5%A6%872%E4%BA%BF%E7%90%86%E8%B4%A2%E4%BA%8F%E6%8D%9F%E5%A7%8B%E6%9C%AB"
            }
          ],
          "rank": 19
        },
        {
          "title": "马龙许昕晋级全锦赛男双四强",
          "titleOrig": "",
          "url": "https://www.zhihu.com/search?q=%E9%A9%AC%E9%BE%99%E8%AE%B8%E6%98%95%E6%99%8B%E7%BA%A7%E5%85%A8%E9%94%A6%E8%B5%9B%E7%94%B7%E5%8F%8C%E5%9B%9B%E5%BC%BA",
          "source": "知乎热榜",
          "sourceId": "zhihu",
          "tier": "c",
          "cat": "cn",
          "region": "中国",
          "lang": "zh",
          "publishedAt": null,
          "desc": "",
          "hotLabel": "#3",
          "summary": "马龙和许昕晋级全锦赛男双四强。",
          "analysis": "马龙和许昕的晋级体现了中国乒乓球运动员的高水平。这一事件对国内乒乓球运动的发展有积极推动作用，有助于提升国家在体育领域的国际地位。后续可能带来更多体育赛事的关注和参与。",
          "keywords": [
            "乒乓球",
            "马龙",
            "许昕",
            "体育",
            "全锦赛"
          ],
          "category": "international",
          "importance": 60,
          "sources": [
            {
              "name": "知乎热榜",
              "url": "https://www.zhihu.com/search?q=%E9%A9%AC%E9%BE%99%E8%AE%B8%E6%98%95%E6%99%8B%E7%BA%A7%E5%85%A8%E9%94%A6%E8%B5%9B%E7%94%B7%E5%8F%8C%E5%9B%9B%E5%BC%BA"
            }
          ],
          "rank": 20
        }
      ]
    }
  }
}